{
    "Igrork": {
        "loves": [
            "Mango",
            "Almond",
            "Cassava Cake",
            "Teff",
            "Porridge",
            "Dried Sponge",
            "Beryl",
            "Dried Date",
            "Pickled Beets",
            "Sauerkraut"
        ],
        "birthday": "Winter 15"
    },
    "Garrek": {
        "loves": [
            "Mango",
            "Beets Juice",
            "Duxelles",
            "Jasper",
            "Mushroom Tart",
            "Seaweed",
            "Mushroom Cheese",
            "Mead"
        ],
        "birthday": "Spring 16"
    },
    "Inza": {
        "loves": [
            "Mango",
            "Strawberry",
            "Broccoli",
            "Coconut Milk Butter",
            "Trumpet",
            "Medusalion",
            "Fish Taco",
            "Pomegranate Toast",
            "Mint",
            "Peridot",
            "Aged Sea Kale Wine",
            "River Fish"
        ],
        "birthday": "Fall 12"
    },
    "Tare": {
        "loves": [
            "Mango",
            "Chile",
            "Sunflower Oil",
            "Oil Cake",
            "Oregano",
            "Red Meat Lard",
            "White Meat",
            "Wild Rice",
            "Sesame Mead",
            "Parsley",
            "Beryl",
            "Broccoli Vinegar",
            "Butter",
            "Smoked Fish"
        ],
        "birthday": "Summer 18"
    },
    "Jelrod": {
        "loves": [
            "Mango",
            "Winter Peas",
            "Buns",
            "Milanesa",
            "Smoked Red Meat",
            "Fermented Wild Rice",
            "Jasper",
            "Gold",
            "Dried Coconut",
            "Aged Wine",
            "Aged Cheese"
        ],
        "birthday": "Spring 7"
    },
    "Ata": {
        "loves": [
            "Strawberry",
            "Wild Grapes",
            "Strawberry Juice",
            "Fruit Crumble",
            "Pumpkin Pie",
            "Alma Juice",
            "Copper",
            "Obsidian",
            "Prickly Pear",
            "Aged Ibex Milk Cheese",
            "Junglefowl Feather",
            "Dried Mango"
        ],
        "birthday": "Fall 2"
    },
    "Ibon": {
        "loves": [
            "Mango",
            "Sunflower",
            "Kohlrabi",
            "Pomegranate",
            "Pineapple",
            "Sushi",
            "Smorrebrod",
            "Pink Shell",
            "Datura Flower",
            "Amethyst",
            "Wild Rye Beer"
        ],
        "birthday": "Spring 16"
    },
    "Kocha": {
        "loves": [
            "Mango",
            "Aged Wine",
            "Oregano Soap",
            "Cherry Jam",
            "Chamomile",
            "Mint",
            "File:Banana Chips L.png",
            "Banana Chips"
        ],
        "birthday": "Unknown"
    },
    "Yakuan_Islands": {
        "loves": [],
        "birthday": "Unknown"
    },
    "Characters?action=purge": {
        "loves": [],
        "birthday": "Unknown"
    },
    "Voda": {
        "loves": [
            "Mango",
            "Buckwheat",
            "Strawberry Juice",
            "Oats Cheese",
            "Sundried Tomato",
            "Popcorn",
            "Ramen",
            "Tomato",
            "Oysters",
            "Pineapple Mead",
            "Lavender",
            "Wild Honey"
        ],
        "birthday": "Winter 6"
    },
    "Exchange": {
        "loves": [],
        "birthday": "Unknown"
    },
    "Ugvin": {
        "loves": [
            "Mango",
            "Gold",
            "Dried Banana",
            "Dried Fig",
            "File:Kale Krisps.png",
            "Kale Krisps",
            "Rosemary Soap",
            "Fig Jam",
            "Pink Shell",
            "Yarn",
            "Aged Wine"
        ],
        "birthday": "Unknown"
    },
    "Sayra": {
        "loves": [
            "Mango",
            "Nacre",
            "Popcorn",
            "White Strawberry",
            "Currants Jam",
            "Lavender Soap",
            "Mulled Wine",
            "Aged Wine",
            "Aged Cheese"
        ],
        "birthday": "Unknown"
    },
    "Pachan_Clan": {
        "loves": [],
        "birthday": "Unknown"
    },
    "Characters?oldid=33675": {
        "loves": [],
        "birthday": "Unknown"
    },
    "Cooking": {
        "loves": [],
        "birthday": "Unknown"
    },
    "Smoke_Signals": {
        "loves": [],
        "birthday": "Unknown"
    },
    "Granan": {
        "loves": [
            "Mango",
            "Grape Wine"
        ],
        "birthday": "Unknown"
    },
    "Acre": {
        "loves": [
            "Mango",
            "Avocado",
            "Wheat Beer",
            "Copper",
            "Obsidian",
            "Potato Salad",
            "Aged Wild Grapes Wine",
            "Tin",
            "Tomato Honey"
        ],
        "birthday": "Unknown"
    },
    "Farming": {
        "loves": [],
        "birthday": "Unknown"
    },
    "Bug_Catching": {
        "loves": [],
        "birthday": "Unknown"
    },
    "Azkel": {
        "loves": [
            "Mango",
            "Pierogi",
            "Prickly Pear Jam",
            "Mint Soap",
            "Mead"
        ],
        "birthday": "Unknown"
    },
    "Yakuan_Clan": {
        "loves": [],
        "birthday": "Unknown"
    },
    "Maeri": {
        "loves": [
            "Mango",
            "Sunflower",
            "Olive",
            "Sunflower Oil",
            "Sauerkraut",
            "Dumplings",
            "Willow Bark",
            "Beans Plant Meat",
            "Pickled Beets",
            "Amethyst",
            "Dried Sponge"
        ],
        "birthday": "Unknown"
    },
    "Crafting": {
        "loves": [],
        "birthday": "Unknown"
    },
    "Solo": {
        "loves": [
            "Mango",
            "Alfalfa Soap",
            "Cole Slaw",
            "Jam"
        ],
        "birthday": "Winter 2"
    },
    "Roots_of_Pacha": {
        "loves": [],
        "birthday": "Unknown"
    },
    "Fishing": {
        "loves": [],
        "birthday": "Unknown"
    },
    "Calendar": {
        "loves": [],
        "birthday": "Unknown"
    },
    "Mograni_Clan": {
        "loves": [],
        "birthday": "Unknown"
    },
    "Havri": {
        "loves": [
            "Mango",
            "File:Jam .png",
            "Citron Jam",
            "Poached Egg",
            "File:Rose Hips Soap.png",
            "Rose Hips Soap",
            "Mead",
            "Honey"
        ],
        "birthday": "Unknown"
    },
    "Ranching": {
        "loves": [],
        "birthday": "Unknown"
    },
    "Characters?action=info": {
        "loves": [],
        "birthday": "Unknown"
    },
    "Don": {
        "loves": [],
        "birthday": "Unknown"
    },
    "Tutorials": {
        "loves": [],
        "birthday": "Unknown"
    },
    "Vuak": {
        "loves": [
            "Mango",
            "Pumpkin",
            "Strawberry Juice",
            "Gemstone",
            "Hummus",
            "Baba Ganoush",
            "Mandrake",
            "Pickled Beets"
        ],
        "birthday": "Unknown"
    },
    "Tetih": {
        "loves": [
            "Mango",
            "Coconut",
            "Coconut Milk Butter",
            "Aged Wine",
            "Cassava",
            "Trumpet",
            "Medusalion",
            "Onion Soup",
            "Wild Raisins",
            "Dried Date",
            "Amethyst",
            "Gold",
            "Sapphire"
        ],
        "birthday": "Unknown"
    },
    "Characters?action=pagevalues": {
        "loves": [],
        "birthday": "Unknown"
    },
    "Okka": {
        "loves": [
            "Mango",
            "Avocado",
            "Roast Meat",
            "Ostrich Egg",
            "Citronella",
            "Sunflower Mead",
            "Sapphire"
        ],
        "birthday": "Winter 24"
    },
    "Martina": {
        "loves": [],
        "birthday": "Unknown"
    },
    "Grob": {
        "loves": [
            "Mango",
            "Beets",
            "Potato",
            "Bife",
            "Zeus",
            "Ostrich Egg Mayonnaise",
            "Smoked Red Meat",
            "Tomato Honey",
            "Pickled Tomato"
        ],
        "birthday": "Summer 3"
    },
    "Brah": {
        "loves": [
            "Mango",
            "Strawberry Juice",
            "Potato",
            "Coconut",
            "Arroz Con Leche",
            "Fried Eggs",
            "Fruit Platter",
            "Goat Cheese",
            "Strawberry",
            "Mango Juice",
            "Bear Claw",
            "Dried Alma",
            "Peridot"
        ],
        "birthday": "Unknown"
    },
    "Tayta": {
        "loves": [
            "Mango",
            "Fig Cheese Pizza",
            "Rose Hips Soap",
            "Grapes Jam",
            "Pink Shell",
            "Best Quality Bugs"
        ],
        "birthday": "Unknown"
    },
    "Trapping": {
        "loves": [],
        "birthday": "Unknown"
    },
    "Koli": {
        "loves": [
            "Mango",
            "Gemstone"
        ],
        "birthday": "Unknown"
    },
    "Gifting": {
        "loves": [],
        "birthday": "Unknown"
    },
    "Dishes": {
        "loves": [],
        "birthday": "Unknown"
    },
    "Vor": {
        "loves": [
            "Mango",
            "Pomegranate Juice",
            "Strawberry Juice",
            "Arroz Con Leche",
            "Marzipan",
            "Parfait",
            "Poop",
            "Dried Red Meat",
            "Smoked Red Meat",
            "Cheese"
        ],
        "birthday": "Unknown"
    },
    "Nann": {
        "loves": [
            "Mango",
            "Strawberry Jam",
            "Roast Meat",
            "Camomile Soap",
            "Pomegranate"
        ],
        "birthday": "Unknown"
    },
    "Reese": {
        "loves": [
            "Mango",
            "Sunflower",
            "Falafel",
            "Boar Fur",
            "Ostrich Feather",
            "Nacre",
            "Strange Mushroom",
            "Lavender",
            "Aged Wine",
            "Wine",
            "Aged Cheese",
            "Herb Cheese",
            "Mushroom Cheese"
        ],
        "birthday": "Unknown"
    },
    "Mana": {
        "loves": [
            "Mango",
            "Quinoa",
            "Tomato Juice",
            "Carrot Juice",
            "Coconut Milk",
            "Almond Milk Cheese",
            "Tomato Bisque",
            "Pineapple Chicken",
            "Pickled Garlic",
            "Cabbage Vinegar"
        ],
        "birthday": "Summer 14"
    },
    "Zelk": {
        "loves": [
            "Mango",
            "Eggplant",
            "Sesame Oil",
            "Beets Juice",
            "Duxelles",
            "Goat Cheese",
            "Ostrich Egg Mayonnaise",
            "Dried Date",
            "Beryl",
            "Aged Kohlrabi Wine",
            "Wild Honey",
            "Mushroom",
            "Pickled Egg"
        ],
        "birthday": "Unknown"
    },
    "Ideas": {
        "loves": [],
        "birthday": "Unknown"
    },
    "Vallah": {
        "loves": [
            "Mango",
            "Kohlrabi",
            "Dried Chile",
            "Smoked Plant Meat",
            "Ensalada Criolla",
            "Lentil Pie",
            "Oregano",
            "Rosemary",
            "Copper",
            "Mint",
            "Amethyst",
            "Smoked Stargazer",
            "Pumpkin Mead"
        ],
        "birthday": "Unknown"
    },
    "Mograni_Tundra": {
        "loves": [],
        "birthday": "Unknown"
    },
    "Accessories": {
        "loves": [],
        "birthday": "Unknown"
    },
    "To": {
        "loves": [],
        "birthday": "Unknown"
    },
    "Ash": {
        "loves": [
            "Mango",
            "Parsley Soap",
            "Sushi",
            "Citron Jam",
            "Avocado",
            "White Strawberry",
            "Mango"
        ],
        "birthday": "Unknown"
    },
    "The_Land": {
        "loves": [],
        "birthday": "Unknown"
    },
    "Brub": {
        "loves": [
            "Mango",
            "Wild Raisins",
            "Almond Milk",
            "Curry",
            "Beans",
            "Dried Coconut",
            "Sea Kale Mulled Wine",
            "Fermented Oysters",
            "Pickled Porcupine"
        ],
        "birthday": "Unknown"
    },
    "Illoe": {
        "loves": [
            "Mango",
            "Sunflower",
            "Wild Grapes Juice",
            "Wheat Beer",
            "Empanadas",
            "Locro",
            "Nacre",
            "Watercress",
            "Burdock Root",
            "Guanaco Fur Yarn",
            "Gold",
            "Pickled Beets"
        ],
        "birthday": "Spring 28"
    },
    "Furniture": {
        "loves": [],
        "birthday": "Unknown"
    },
    "Gin": {
        "loves": [
            "Mango",
            "Corn",
            "Potato",
            "Trumpet",
            "Medusalion",
            "Buns",
            "Amethyst",
            "Mayo",
            "Aged Wine",
            "Smoked Meat"
        ],
        "birthday": "Unknown"
    },
    "Nari": {
        "loves": [
            "Mango",
            "Amaranth",
            "Cabbage",
            "Dried Chili",
            "Kefir Pancakes",
            "Elecampane",
            "Copper",
            "Pickled Chitons",
            "Beryl",
            "Pickled Chile",
            "Aged Wine",
            "Aged Cheese"
        ],
        "birthday": "Unknown"
    },
    "Ada": {
        "loves": [
            "Mango",
            "Olive Oil",
            "Coconut Milk Butter",
            "Steamed Vegetables",
            "Mandrake",
            "Willow Bark",
            "Rose Hips",
            "Seaweed",
            "Red Mushroom",
            "Burdock Root",
            "Eggplant"
        ],
        "birthday": "Spring 4"
    },
    "Jukk": {
        "loves": [
            "Mango",
            "Chile",
            "Prickly Pear",
            "Broccoli",
            "Focaccia",
            "Humita",
            "Ostrich Feather",
            "Nacre",
            "Bones",
            "Sapphire",
            "Aged Wild Grapes Wine",
            "Gold",
            "Yarn"
        ],
        "birthday": "Unknown"
    },
    "Cohh": {
        "loves": [
            "Mango",
            "Corn",
            "Blue Corn Tortilla",
            "File:Milk Thistle Soap.png",
            "Milk Thistle Soap",
            "File:Citronella Soap.png",
            "Citronella Soap",
            "File:Grape Jam.png",
            "Grape Jam",
            "Poached Egg"
        ],
        "birthday": "Unknown"
    },
    "Jizu": {
        "loves": [
            "Mango",
            "Fennel",
            "Pine Cone",
            "Trumpet",
            "Medusalion",
            "Tamales",
            "Guanaco Fur Yarn",
            "Sunflower Mead",
            "Citronella",
            "Tomato Honey",
            "Sardius"
        ],
        "birthday": "Unknown"
    },
    "Fayra": {
        "loves": [
            "Mango",
            "Curd Cheese",
            "Pineapple Jam",
            "Muscovado Sugar",
            "Pomegranate",
            "Bugs"
        ],
        "birthday": "Unknown"
    },
    "Beach": {
        "loves": [],
        "birthday": "Unknown"
    },
    "Touk": {
        "loves": [
            "Mango",
            "Potato",
            "Wild Grapes Juice",
            "Pineapple",
            "Pizza",
            "Spaghetti",
            "Datura Flower",
            "Ostrich Egg Mayo",
            "Dried Red Meat",
            "Goat Cheese",
            "Aged Ibex Milk Cheese",
            "Ibex Milk Herb Cheese",
            "Mushroom Ibex Milk Cheese",
            "Alfalfa",
            "Peridot",
            "Pineapple Mead"
        ],
        "birthday": "Unknown"
    },
    "Getting_started": {
        "loves": [],
        "birthday": "Unknown"
    },
    "Processors": {
        "loves": [],
        "birthday": "Unknown"
    },
    "Zeda": {
        "loves": [
            "Mango",
            "Cassava Cake",
            "Chile",
            "Kohlrabi",
            "Garlic",
            "Pomegranate Juice",
            "Wild Raisins",
            "Dried Mango",
            "Meat Filled Squash",
            "Smoked Red Meat",
            "Mint",
            "Aged Prickly Pear Wine",
            "Silver",
            "Gold",
            "Amethyst"
        ],
        "birthday": "Fall 28"
    },
    "Prophecies": {
        "loves": [],
        "birthday": "Unknown"
    },
    "Javvi": {
        "loves": [
            "Mango",
            "Dill Soap",
            "Tomato Carpaccio",
            "Banana Jam",
            "File:Dried.png",
            "Sundried Yellow Tomato"
        ],
        "birthday": "Unknown"
    },
    "Characters?action=edit": {
        "loves": [],
        "birthday": "Unknown"
    },
    "Krak": {
        "loves": [
            "Sunflower",
            "Cabbage",
            "Mango Juice",
            "Calamari Salad",
            "Seaweed Salad",
            "Ostrich Feather",
            "Horns",
            "Dried Strawberry",
            "Strawberry Honey",
            "Sapphire",
            "Wild Rice Beer"
        ],
        "birthday": "Unknown"
    },
    "Era": {
        "loves": [
            "Mango",
            "Chile",
            "Pumpkin",
            "Almond Milk",
            "Injera",
            "Souffle",
            "Oregano",
            "Peridot",
            "Citron Vinegar",
            "Silver",
            "Avocado Oil"
        ],
        "birthday": "Fall 11"
    },
    "Clothing": {
        "loves": [],
        "birthday": "Unknown"
    },
    "Frer": {
        "loves": [
            "Mango",
            "Kohlrabi",
            "Tomato Juice",
            "Mediterranean Grilled Fish",
            "Pasta of the Sea",
            "Zeus",
            "Trumpet",
            "Sardius",
            "Bear Claw"
        ],
        "birthday": "Unknown"
    },
    "Glyp": {
        "loves": [],
        "birthday": "Unknown"
    },
    "Ron": {
        "loves": [
            "Roasted Vegetables",
            "Strawberry Mulled Wine",
            "Wheat Beer",
            "Grain",
            "Juice",
            "Aged Wine"
        ],
        "birthday": "Unknown"
    },
    "Trading": {
        "loves": [],
        "birthday": "Unknown"
    },
    "Characters": {
        "loves": [],
        "birthday": "Unknown"
    },
    "Hunna": {
        "loves": [
            "Mango",
            "Mango"
        ],
        "birthday": "Unknown"
    },
    "Todu": {
        "loves": [
            "Mango"
        ],
        "birthday": "Unknown"
    },
    "Jungle": {
        "loves": [],
        "birthday": "Unknown"
    },
    "Savanna": {
        "loves": [],
        "birthday": "Unknown"
    },
    "Dag": {
        "loves": [
            "Mango",
            "Potato Salad",
            "File:Any L.png",
            "Dish",
            "Jam"
        ],
        "birthday": "Unknown"
    },
    "Prosperity": {
        "loves": [],
        "birthday": "Unknown"
    },
    "Caves": {
        "loves": [],
        "birthday": "Unknown"
    },
    "Jiyla": {
        "loves": [
            "Mango",
            "File:Grape Jam.png",
            "Grape Jam",
            "Crab Cakes",
            "File:Lavender Soap.png",
            "Lavender Soap",
            "File:White Strawberry Jam.png",
            "White Strawberry Jam",
            "Aged Wine",
            "Yarn"
        ],
        "birthday": "Unknown"
    },
    "Pellek": {
        "loves": [
            "Mango",
            "Mango Juice",
            "Rosemary Soap",
            "Grape Juice",
            "Strawberry Juice",
            "File:Mussel Shell L.png",
            "Mussel Shell",
            "File:Hot Chocolate L.png",
            "Hot Chocolate"
        ],
        "birthday": "Unknown"
    },
    "Update_History": {
        "loves": [],
        "birthday": "Unknown"
    },
    "Nokk": {
        "loves": [
            "Mango",
            "Carrot",
            "Sundried Tomato",
            "Sesame Oil",
            "Tomato",
            "Maccu",
            "Oregano",
            "Ibex Milk Sour Cream",
            "Wheat Flour",
            "Smoked Red Meat",
            "Wild Rice",
            "Avocado Oil",
            "Rosemary",
            "Peridot",
            "Pineapple Mead Vinegar"
        ],
        "birthday": "Spring 22"
    },
    "Anda": {
        "loves": [
            "Mango",
            "Alma Jam",
            "Farikal",
            "Vanilla",
            "Coal"
        ],
        "birthday": "Unknown"
    },
    "Tools": {
        "loves": [],
        "birthday": "Unknown"
    },
    "Jag": {
        "loves": [
            "Sesame",
            "Meat Stew",
            "Ibex Milk Herb Cheese",
            "Hardwood",
            "Smoked Red Meat",
            "Lavender",
            "Pickled Carrot",
            "Honey"
        ],
        "birthday": "Fall 8"
    },
    "Festivals_%26_Events": {
        "loves": [],
        "birthday": "Unknown"
    },
    "Relationships": {
        "loves": [],
        "birthday": "Unknown"
    },
    "Croll": {
        "loves": [
            "Mango",
            "Sauerkraut",
            "Roasted Fish",
            "Pickled Beets",
            "Pickled Garlic",
            "Pickled Oysters",
            "Alma Wine",
            "Cabbage Wine",
            "Aged Cabbage Wine"
        ],
        "birthday": "Fall 18"
    },
    "Daari": {
        "loves": [
            "Mango",
            "Almond Milk Butter",
            "Hummus",
            "Frittata",
            "Milk Thistle",
            "Oregano",
            "Ostrich Feather",
            "Agate",
            "Amaranth"
        ],
        "birthday": "Winter 8"
    },
    "Akhi": {
        "loves": [
            "Mango",
            "Mint Soap",
            "Black Sesame Oil",
            "Sesame Oil",
            "Prickly Pear Jam",
            "Fig Cheese Pizza",
            "Mango",
            "Butter"
        ],
        "birthday": "Unknown"
    }
}